rsaitehu/matplot3d.py
rsaitehu_matplot3d-0.0.1.dist-info/METADATA
rsaitehu_matplot3d-0.0.1.dist-info/WHEEL
rsaitehu_matplot3d-0.0.1.dist-info/top_level.txt
rsaitehu_matplot3d-0.0.1.dist-info/RECORD
